{
    "MMDs": {
        "mean": 0.024860143549071272,
        "sd": 0.0023523875103999407
    },
    "auroc": {
        "mean": 0.7616179573643443,
        "sd": 0.02222689675309083
    },
    "auprc": {
        "mean": 0.6589446240170055,
        "sd": 0.033526562715737424
    },
    "remaining samples": {
        "mean": 2197.65,
        "sd": 7.754192414429759
    },
    "all_samples": 2250,
    "AGEP_relative_bias": {
        "bias mean": 0.582311585951717,
        "bias sd": 0.2139379331908411,
        "wasserstein mean": 0.2969589017078835,
        "wasserstein sd": 0.0256799601277421
    },
    "WKHP_relative_bias": {
        "bias mean": 0.4311328450317212,
        "bias sd": 0.17720432357521543,
        "wasserstein mean": 0.3387034647989433,
        "wasserstein sd": 0.04990149187539656
    },
    "COW_Employee of a private for-profit company or business, or of an individual, for wages, salary, or commissions_relative_bias": {
        "bias mean": 3.423509710116708,
        "bias sd": 0.5643425474303316,
        "wasserstein mean": 0.04673569650174681,
        "wasserstein sd": 0.0075800314953406766
    },
    "COW_Employee of a private not-for-profit, tax-exempt, or charitable organization_relative_bias": {
        "bias mean": 5.807659068785087,
        "bias sd": 2.6170155910099084,
        "wasserstein mean": 0.016381156269501106,
        "wasserstein sd": 0.007310075265902393
    },
    "COW_Federal government employee_relative_bias": {
        "bias mean": 21.76870272934174,
        "bias sd": 5.0905775216347475,
        "wasserstein mean": 0.03521528578780222,
        "wasserstein sd": 0.006828998168720188
    },
    "COW_Local government employee (city, county, etc.)_relative_bias": {
        "bias mean": 3.6535904720828953,
        "bias sd": 1.9340178694159686,
        "wasserstein mean": 0.01060277880517783,
        "wasserstein sd": 0.005094673840550887
    },
    "COW_Self-employed in own incorporated business, professional practice or farm_relative_bias": {
        "bias mean": 16.033411988401472,
        "bias sd": 5.247193869043899,
        "wasserstein mean": 0.030796867028888713,
        "wasserstein sd": 0.006787316576332402
    },
    "COW_Self-employed in own not incorporated business, professional practice, or farm_relative_bias": {
        "bias mean": 2.310970013323243,
        "bias sd": 1.291928327490096,
        "wasserstein mean": 0.00704406287814478,
        "wasserstein sd": 0.003901491480081564
    },
    "COW_State government employee_relative_bias": {
        "bias mean": 10.810323408019753,
        "bias sd": 2.3254135763894577,
        "wasserstein mean": 0.022695530422062737,
        "wasserstein sd": 0.004584959765045582
    },
    "COW_Working without pay in family business or farm_relative_bias": {
        "bias mean": 100.0,
        "bias sd": 0.0,
        "wasserstein mean": 0.050185406686870014,
        "wasserstein sd": 0.013273907037466948
    },
    "SCHL_1 or more years of college credit, no degree_relative_bias": {
        "bias mean": 3.053961708735611,
        "bias sd": 1.4282123077408224,
        "wasserstein mean": 0.013588860488269256,
        "wasserstein sd": 0.006429151297331285
    },
    "SCHL_12th grade - no diploma_relative_bias": {
        "bias mean": 19.028334172933732,
        "bias sd": 8.089126682209587,
        "wasserstein mean": 0.027653760792677083,
        "wasserstein sd": 0.007667393054812359
    },
    "SCHL_Associate's degree_relative_bias": {
        "bias mean": 1.6431546415089684,
        "bias sd": 1.1060822400934047,
        "wasserstein mean": 0.004791833765831614,
        "wasserstein sd": 0.003316731350913835
    },
    "SCHL_Bachelor's degree_relative_bias": {
        "bias mean": 2.0762048844686514,
        "bias sd": 0.9408495637445581,
        "wasserstein mean": 0.011631982756606447,
        "wasserstein sd": 0.005227947628517546
    },
    "SCHL_Doctorate degree_relative_bias": {
        "bias mean": 25.300604173869548,
        "bias sd": 5.802481106261086,
        "wasserstein mean": 0.035998606548890276,
        "wasserstein sd": 0.006037608740636371
    },
    "SCHL_GED or alternative credential_relative_bias": {
        "bias mean": 21.53931866553109,
        "bias sd": 4.89535579738558,
        "wasserstein mean": 0.0311629623654903,
        "wasserstein sd": 0.007122997657205428
    },
    "SCHL_Grade 1_relative_bias": {
        "bias mean": 100.0,
        "bias sd": 0.0,
        "wasserstein mean": 0.018820716000951306,
        "wasserstein sd": 0.019432931122135302
    },
    "SCHL_Grade 10_relative_bias": {
        "bias mean": 73.40480579816463,
        "bias sd": 36.498874113330395,
        "wasserstein mean": 0.06620831541701153,
        "wasserstein sd": 0.03406686571414049
    },
    "SCHL_Grade 11_relative_bias": {
        "bias mean": 20.758218186759898,
        "bias sd": 8.223479503718952,
        "wasserstein mean": 0.02672198188805669,
        "wasserstein sd": 0.008151562487347568
    },
    "SCHL_Grade 2_relative_bias": {
        "bias mean": 100.00000000000001,
        "bias sd": 1.6202867315927535e-14,
        "wasserstein mean": 0.05265175969178032,
        "wasserstein sd": 0.026652611040200832
    },
    "SCHL_Grade 3_relative_bias": {
        "bias mean": 100.0,
        "bias sd": 0.0,
        "wasserstein mean": 0.05517322790750403,
        "wasserstein sd": 0.016254527249486814
    },
    "SCHL_Grade 4_relative_bias": {
        "bias mean": 100.0,
        "bias sd": 0.0,
        "wasserstein mean": 0.04433714738930942,
        "wasserstein sd": 0.015377631712306406
    },
    "SCHL_Grade 5_relative_bias": {
        "bias mean": 100.0,
        "bias sd": 0.0,
        "wasserstein mean": 0.05511058540035898,
        "wasserstein sd": 0.01680982131061822
    },
    "SCHL_Grade 6_relative_bias": {
        "bias mean": 27.144926913565154,
        "bias sd": 7.344382323498262,
        "wasserstein mean": 0.03359002365124807,
        "wasserstein sd": 0.007450436758115274
    },
    "SCHL_Grade 7_relative_bias": {
        "bias mean": 100.0,
        "bias sd": 0.0,
        "wasserstein mean": 0.051233854885073274,
        "wasserstein sd": 0.01774792794571162
    },
    "SCHL_Grade 8_relative_bias": {
        "bias mean": 100.0,
        "bias sd": 0.0,
        "wasserstein mean": 0.07691693331631058,
        "wasserstein sd": 0.023502549575653932
    },
    "SCHL_Grade 9_relative_bias": {
        "bias mean": 39.3635476640085,
        "bias sd": 11.252371982482467,
        "wasserstein mean": 0.03937488240082797,
        "wasserstein sd": 0.008375990590083381
    },
    "SCHL_Kindergarten_relative_bias": {
        "bias mean": 100.0,
        "bias sd": 0.0,
        "wasserstein mean": 0.017427223821779976,
        "wasserstein sd": 0.027370544769848452
    },
    "SCHL_Master's degree_relative_bias": {
        "bias mean": 1.5388107991696751,
        "bias sd": 1.1526752524014943,
        "wasserstein mean": 0.005160279119898546,
        "wasserstein sd": 0.003826339284153862
    },
    "SCHL_No schooling completed_relative_bias": {
        "bias mean": 20.61197380252684,
        "bias sd": 5.542817238239309,
        "wasserstein mean": 0.02723261805252351,
        "wasserstein sd": 0.006357411116933286
    },
    "SCHL_Nursery school, preschool_relative_bias": {
        "bias mean": 54.999999999999986,
        "bias sd": 49.74937185533099,
        "wasserstein mean": 0.01843087839318,
        "wasserstein sd": 0.018716645487171918
    },
    "SCHL_Professional degree beyond a bachelor's degree_relative_bias": {
        "bias mean": 18.013990799932976,
        "bias sd": 3.9318937064573785,
        "wasserstein mean": 0.030521415425593158,
        "wasserstein sd": 0.005080505406505409
    },
    "SCHL_Regular high school diploma_relative_bias": {
        "bias mean": 2.886460095613896,
        "bias sd": 1.2578915296572117,
        "wasserstein mean": 0.013180646647085603,
        "wasserstein sd": 0.005835539129383933
    },
    "SCHL_Some college, but less than 1 year_relative_bias": {
        "bias mean": 3.3913818125595165,
        "bias sd": 2.120194953186,
        "wasserstein mean": 0.008806214378697807,
        "wasserstein sd": 0.005309925456123727
    },
    "MAR_Divorced_relative_bias": {
        "bias mean": 5.523259569353269,
        "bias sd": 1.6312338652165228,
        "wasserstein mean": 0.017054746184023202,
        "wasserstein sd": 0.004995015905824971
    },
    "MAR_Married_relative_bias": {
        "bias mean": 0.9431514904916332,
        "bias sd": 0.5141127665212232,
        "wasserstein mean": 0.00992035834790583,
        "wasserstein sd": 0.005438481542164045
    },
    "MAR_Never married or under 15 years old_relative_bias": {
        "bias mean": 2.402844317946325,
        "bias sd": 0.4904575456545793,
        "wasserstein mean": 0.017707048187347033,
        "wasserstein sd": 0.003641809471482282
    },
    "MAR_Separated_relative_bias": {
        "bias mean": 22.66895660946896,
        "bias sd": 7.4799782514850195,
        "wasserstein mean": 0.029969547488184665,
        "wasserstein sd": 0.00747666337228694
    },
    "MAR_Widowed_relative_bias": {
        "bias mean": 28.29622668852476,
        "bias sd": 8.472857138132685,
        "wasserstein mean": 0.03418566802183366,
        "wasserstein sd": 0.008538046886074707
    },
    "RELP_Adopted son or daughter_relative_bias": {
        "bias mean": 100.0,
        "bias sd": 0.0,
        "wasserstein mean": 0.045187327006252095,
        "wasserstein sd": 0.01738151450875345
    },
    "RELP_Biological son or daughter_relative_bias": {
        "bias mean": 2.248548098503708,
        "bias sd": 1.309180662732178,
        "wasserstein mean": 0.00865905245762303,
        "wasserstein sd": 0.004937201387893625
    },
    "RELP_Brother or sister_relative_bias": {
        "bias mean": 29.702865547414753,
        "bias sd": 8.659899242589049,
        "wasserstein mean": 0.0383241980211092,
        "wasserstein sd": 0.008563751532703591
    },
    "RELP_Father or mother_relative_bias": {
        "bias mean": 27.952941202828764,
        "bias sd": 20.0217926974551,
        "wasserstein mean": 0.02745813283496657,
        "wasserstein sd": 0.02159459829956584
    },
    "RELP_Foster child_relative_bias": {
        "bias mean": 100.0,
        "bias sd": 0.0,
        "wasserstein mean": 0.005107863228865261,
        "wasserstein sd": 0.01532358968659578
    },
    "RELP_Grandchild_relative_bias": {
        "bias mean": 100.0,
        "bias sd": 0.0,
        "wasserstein mean": 0.09491045215621524,
        "wasserstein sd": 0.018000584237069493
    },
    "RELP_Housemate or roommate_relative_bias": {
        "bias mean": 21.89225577130011,
        "bias sd": 5.164674055834698,
        "wasserstein mean": 0.036910781819278815,
        "wasserstein sd": 0.0070738854879100355
    },
    "RELP_Husband/wife_relative_bias": {
        "bias mean": 1.0638204064578205,
        "bias sd": 0.6754059949828796,
        "wasserstein mean": 0.005698772960487865,
        "wasserstein sd": 0.00360813679411921
    },
    "RELP_Institutionalized group quarters population_relative_bias": {
        "bias mean": 100.0,
        "bias sd": 0.0,
        "wasserstein mean": 0.06589852066508496,
        "wasserstein sd": 0.016623042644071804
    },
    "RELP_Noninstitutionalized group quarters population_relative_bias": {
        "bias mean": 26.46113559152493,
        "bias sd": 5.975987380190566,
        "wasserstein mean": 0.04007484007057043,
        "wasserstein sd": 0.006722168517999825
    },
    "RELP_Other nonrelative_relative_bias": {
        "bias mean": 33.71618753901296,
        "bias sd": 10.879264843680694,
        "wasserstein mean": 0.03896651140444157,
        "wasserstein sd": 0.006581959774098968
    },
    "RELP_Other relative_relative_bias": {
        "bias mean": 30.265096638635175,
        "bias sd": 8.88858096339966,
        "wasserstein mean": 0.03534803512280828,
        "wasserstein sd": 0.007926365898523573
    },
    "RELP_Parent-in-law_relative_bias": {
        "bias mean": 100.0,
        "bias sd": 2.8064189419483652e-14,
        "wasserstein mean": 0.03750257282402848,
        "wasserstein sd": 0.015675198293685095
    },
    "RELP_Reference person_relative_bias": {
        "bias mean": 0.9694954305171514,
        "bias sd": 0.5539179248082285,
        "wasserstein mean": 0.009049659679202602,
        "wasserstein sd": 0.0052222576740928225
    },
    "RELP_Roomer or boarder_relative_bias": {
        "bias mean": 96.17551966362615,
        "bias sd": 16.6705232978121,
        "wasserstein mean": 0.08846005876653382,
        "wasserstein sd": 0.023073515731754247
    },
    "RELP_Son-in-law or daughter-in-law_relative_bias": {
        "bias mean": 58.74481020579113,
        "bias sd": 27.2117806112614,
        "wasserstein mean": 0.05136031893082867,
        "wasserstein sd": 0.027171540992715775
    },
    "RELP_Stepson or stepdaughter_relative_bias": {
        "bias mean": 100.0,
        "bias sd": 0.0,
        "wasserstein mean": 0.07754211334829172,
        "wasserstein sd": 0.01678065008105398
    },
    "RELP_Unmarried partner_relative_bias": {
        "bias mean": 17.676304263021922,
        "bias sd": 3.4131579099386182,
        "wasserstein mean": 0.032601754682540104,
        "wasserstein sd": 0.0057817872740540755
    },
    "SEX_Female_relative_bias": {
        "bias mean": 0.5932003807267434,
        "bias sd": 0.4753781189855226,
        "wasserstein mean": 0.005634978745418174,
        "wasserstein sd": 0.004531236371893714
    },
    "SEX_Male_relative_bias": {
        "bias mean": 0.53524095862477,
        "bias sd": 0.43184331125671965,
        "wasserstein mean": 0.005634978745418247,
        "wasserstein sd": 0.0045312363718941215
    },
    "RAC1P_Alaska Native alone_relative_bias": {
        "bias mean": 100.0,
        "bias sd": 0.0,
        "wasserstein mean": 0.01226872198421459,
        "wasserstein sd": 0.02125004982059692
    },
    "RAC1P_American Indian alone_relative_bias": {
        "bias mean": 100.0,
        "bias sd": 0.0,
        "wasserstein mean": 0.07723330286994637,
        "wasserstein sd": 0.02169592180122844
    },
    "RAC1P_American Indian and Alaska Native tribes specified; or American Indian or Alaska Native, not specified and no other races_relative_bias": {
        "bias mean": 100.0,
        "bias sd": 0.0,
        "wasserstein mean": 0.04718008695306725,
        "wasserstein sd": 0.01890876322505561
    },
    "RAC1P_Asian alone_relative_bias": {
        "bias mean": 2.843456310690336,
        "bias sd": 1.4452453408057395,
        "wasserstein mean": 0.012685778609229554,
        "wasserstein sd": 0.006278967194400016
    },
    "RAC1P_Black or African American alone_relative_bias": {
        "bias mean": 15.721729081228636,
        "bias sd": 4.581360176356489,
        "wasserstein mean": 0.03271155401999276,
        "wasserstein sd": 0.007519948384338241
    },
    "RAC1P_Native Hawaiian and Other Pacific Islander alone_relative_bias": {
        "bias mean": 100.0,
        "bias sd": 0.0,
        "wasserstein mean": 0.05512195288968617,
        "wasserstein sd": 0.01477522910458965
    },
    "RAC1P_Some Other Race alone_relative_bias": {
        "bias mean": 1.6817275181566296,
        "bias sd": 1.3078267183882375,
        "wasserstein mean": 0.006075529333785183,
        "wasserstein sd": 0.004890579844614894
    },
    "RAC1P_Two or More Races_relative_bias": {
        "bias mean": 16.42165674423009,
        "bias sd": 3.3822838942037854,
        "wasserstein mean": 0.032828492698608616,
        "wasserstein sd": 0.006848509210081162
    },
    "RAC1P_White alone_relative_bias": {
        "bias mean": 0.8010715917029465,
        "bias sd": 0.44832746761291353,
        "wasserstein mean": 0.010259734052584322,
        "wasserstein sd": 0.005756802843203862
    },
    "Income_relative_bias": {
        "bias mean": 5.106708856086081,
        "bias sd": 3.288242185601821,
        "wasserstein mean": 6319.4308461203145,
        "wasserstein sd": 1395.7757445719549
    },
    "Binary Income_relative_bias": {
        "bias mean": 7.784138612472321,
        "bias sd": 4.016442448128836,
        "wasserstein mean": 0.034287028235222325,
        "wasserstein sd": 0.018189923052784416
    }
}